firegs/__init__.py
firegs/script.py
firegs/version.py
firegs-0.9.dist-info/LICENSE
firegs-0.9.dist-info/METADATA
firegs-0.9.dist-info/WHEEL
firegs-0.9.dist-info/entry_points.txt
firegs-0.9.dist-info/top_level.txt
firegs-0.9.dist-info/RECORD
