Metadata-Version: 2.1
Name: firegs
Version: 0.9
Summary: A tool to add app to Firebase project from the command line
Home-page: https://github.com/androiddevnotes/firegs
Author: Android Dev Notes
Author-email: awesomedevnotes@gmail.com
Classifier: Programming Language :: Python :: 3
Classifier: License :: OSI Approved :: MIT License
License-File: LICENSE
Requires-Dist: requests
Requires-Dist: google-auth
Requires-Dist: google-auth-httplib2
Requires-Dist: google-auth-oauthlib
Requires-Dist: google-api-python-client
